pilwio/__init__.py
pilwio/pilw.py
pilwio/v1/__init__.py
pilwio/v1/billing.py
pilwio/v1/billing_account.py
pilwio/v1/card.py
pilwio/v1/invoice.py
pilwio/v1/network.py
pilwio/v1/replica.py
pilwio/v1/storage.py
pilwio/v1/token.py
pilwio/v1/vm.py
pilwio_api-1.0.2.dist-info/LICENSE
pilwio_api-1.0.2.dist-info/METADATA
pilwio_api-1.0.2.dist-info/WHEEL
pilwio_api-1.0.2.dist-info/top_level.txt
pilwio_api-1.0.2.dist-info/RECORD
