Metadata-Version: 2.1
Name: pilwio-api
Version: 1.0.2
Summary: Python API wrapper for pilw.io
Home-page: https://github.com/Borks/Pilwio
Author: Borka Martin Orlov
Author-email: borka.orlov@gmail.com
License: UNKNOWN
Platform: UNKNOWN
Classifier: Programming Language :: Python :: 3
Classifier: License :: OSI Approved :: MIT License
Classifier: Operating System :: OS Independent
Requires-Dist: requests
